MANIFEST.in
setup.py
tornado_eventsource/__init__.py
tornado_eventsource/handler.py