Metadata-Version: 1.0
Name: tornado_eventsource
Version: 0.1.0
Summary: EventSource handler for tornado
Home-page: https://github.com/guilhermef/tornado-eventsource
Author: Guilherme Souza
Author-email: guivideojob@gmail.com
License: MIT
Keywords: tornado EventSource event source
Platform: UNKNOWN
